Metadata-Version: 2.2
Name: amazon-braket-qrack-cpu-simulator
Version: 0.4.0
Summary: An open source quantum circuit simulator to be run locally with the Amazon Braket SDK
Home-page: https://github.com/amazon-braket/amazon-braket-qrack-simulator-python
Author: Unitary Fund, Amazon Web Services
License: Apache License 2.0
Keywords: Qrack Amazon AWS Quantum
Classifier: Development Status :: 5 - Production/Stable
Classifier: Intended Audience :: Developers
Classifier: Natural Language :: English
Classifier: License :: OSI Approved :: Apache Software License
Classifier: Programming Language :: Python
Classifier: Programming Language :: Python :: 3.9
Classifier: Programming Language :: Python :: 3.10
Classifier: Programming Language :: Python :: 3.11
Requires-Python: >= 3.9
License-File: LICENSE
License-File: NOTICE
Requires-Dist: pyqrack-cpu>=1.27.0
Requires-Dist: qiskit
Requires-Dist: qiskit_qasm3_import
Requires-Dist: amazon-braket-sdk
Provides-Extra: test
Requires-Dist: black; extra == "test"
Requires-Dist: flake8; extra == "test"
Requires-Dist: flake8-rst-docstrings; extra == "test"
Requires-Dist: isort; extra == "test"
Requires-Dist: pre-commit; extra == "test"
Requires-Dist: pylint; extra == "test"
Requires-Dist: pytest==7.2.0; extra == "test"
Requires-Dist: pytest-benchmark; extra == "test"
Requires-Dist: pytest-cov; extra == "test"
Requires-Dist: pytest-rerunfailures; extra == "test"
Requires-Dist: pytest-xdist; extra == "test"
Requires-Dist: sphinx; extra == "test"
Requires-Dist: sphinx-rtd-theme; extra == "test"
Requires-Dist: sphinxcontrib-apidoc; extra == "test"
Requires-Dist: tox; extra == "test"
Dynamic: author
Dynamic: classifier
Dynamic: description
Dynamic: description-content-type
Dynamic: home-page
Dynamic: keywords
Dynamic: license
Dynamic: provides-extra
Dynamic: requires-dist
Dynamic: requires-python
Dynamic: summary
